{
  "drives": [
    {
      "name": "/dev/vda",
      "alias": "root",
      "mountPath": "/",
      "filesystem": {
        "default": true,
        "type": "btrfs",
        "snapshots": true
      },
      "spacePolicy": "delete"
    },
    {
      "name": "/dev/vdb",
      "spacePolicy": "custom",
      "ptableType": "gpt",
      "partitions": [
        {
          "name": "/dev/vda1",
          "size": {
            "default": false,
            "min": 0,
            "max": 1234567
          },
          "deleteIfNeeded": true,
          "resizeIfNeeded": true
        },
        {
          "name": "/dev/vda2",
          "size": {
            "default": false,
            "min": 1234567,
            "max": 1234567
          },
          "resize": true
        },
        {
          "name": "/dev/vdb3",
          "delete": true
        },
        {
          "size": {
            "default": true,
            "min": 4444,
            "max": 8888
          },
          "mountPath": "swap",
          "filesystem": {
            "default": true,
            "type": "swap"
          }
        },
        {
          "size": {
            "default": false,
            "min": 100000,
            "max": 100000
          },
          "mountPath": "/home",
          "filesystem": {
            "default": false,
            "type": "xfs"
          }
        }
      ]
    }
  ]
}
